{
  "mp-23324": {
    "bg": 1.9500000000000002
  },
  "mp-1192556": {
    "bg": 3.9
  },
  "mp-31307": {
    "bg": 1.8
  },
  "mp-22858": {
    "bg": 2.867
  },
  "mp-2980": {
    "bg": 3.65
  },
  "mp-1192528": {
    "bg": 1.4
  },
  "mp-32594": {
    "bg": 2.3
  },
  "mp-545820": {
    "bg": 2.55
  },
  "mp-1048391": {
    "bg": 2.18
  },
  "mp-1270": {
    "bg": 2.955
  },
  "mp-15724": {
    "bg": 1.0
  },
  "mp-30092": {
    "bg": 2.975
  },
  "mp-13033": {
    "bg": 2.3
  },
  "mp-988": {
    "bg": 5.0
  },
  "mp-6565": {
    "bg": 4.681
  },
  "mp-1205803": {
    "bg": 2.5
  },
  "mp-3094": {
    "bg": 4.8
  },
  "mp-17761": {
    "bg": 2.03
  },
  "mp-1227983": {
    "bg": 3.23
  },
  "mp-1191826": {
    "bg": 2.26
  },
  "mp-27624": {
    "bg": 2.56
  },
  "mp-1221129": {
    "bg": 4.13
  },
  "mp-550514": {
    "bg": 1.9
  },
  "mp-5350": {
    "bg": 3.4
  },
  "mp-10347": {
    "bg": 3.8
  },
  "mp-696805": {
    "bg": 0.5037
  },
  "mp-1747": {
    "bg": 1.9
  },
  "mp-10044": {
    "bg": 1.39
  },
  "mp-1024073": {
    "bg": 3.325
  },
  "mp-1211748": {
    "bg": 2.21
  },
  "mp-23029": {
    "bg": 2.0
  },
  "mp-567910": {
    "bg": 1.8900000000000001
  },
  "mp-1200554": {
    "bg": 4.06
  },
  "mp-510458": {
    "bg": 0.68
  },
  "mp-1200969": {
    "bg": 3.64
  },
  "mp-757233": {
    "bg": 2.68
  },
  "mp-2715259": {
    "bg": 3.86
  },
  "mp-22473": {
    "bg": 2.8
  },
  "mp-1105127": {
    "bg": 0.53
  },
  "mp-569766": {
    "bg": 1.1
  },
  "mp-685194": {
    "bg": 2.0
  },
  "mp-1200713": {
    "bg": 3.22
  },
  "mp-570363": {
    "bg": 0.755
  },
  "mp-35876": {
    "bg": 2.7
  },
  "mp-1104268": {
    "bg": 2.215
  },
  "mp-2969": {
    "bg": 1.7000000000000002
  },
  "mp-634101": {
    "bg": 2.565
  },
  "mp-556210": {
    "bg": 3.42
  },
  "mp-560118": {
    "bg": 3.8200000000000003
  },
  "mp-5193": {
    "bg": 1.0
  },
  "mp-546790": {
    "bg": 2.31
  },
  "mp-1189259": {
    "bg": 1.62
  },
  "mp-1057015": {
    "bg": 0.7
  },
  "mp-1188784": {
    "bg": 3.26
  },
  "mp-2456335": {
    "bg": 3.27
  },
  "mp-9003": {
    "bg": 2.14
  },
  "mp-7440": {
    "bg": 2.0340000000000003
  },
  "mp-541289": {
    "bg": 2.9
  },
  "mp-29530": {
    "bg": 2.63
  },
  "mp-5837": {
    "bg": 4.08
  },
  "mp-22443": {
    "bg": 2.0
  },
  "mp-585963": {
    "bg": 2.07
  },
  "mp-21723": {
    "bg": 0.9
  },
  "mp-567386": {
    "bg": 2.48
  },
  "mp-1095584": {
    "bg": 1.4
  },
  "mp-4531": {
    "bg": 2.92
  },
  "mp-406": {
    "bg": 1.5
  },
  "mp-1238815": {
    "bg": 1.795
  },
  "mp-560798": {
    "bg": 3.2800000000000002
  },
  "mp-19795": {
    "bg": 1.995
  },
  "mp-556516": {
    "bg": 0.79
  },
  "mp-1190": {
    "bg": 2.7
  },
  "mp-1196300": {
    "bg": 1.83
  },
  "mp-11025": {
    "bg": 1.75
  },
  "mp-1188427": {
    "bg": 0.6900000000000001
  },
  "mp-1095180": {
    "bg": 0.95
  },
  "mp-8830": {
    "bg": 1.33
  },
  "mp-29461": {
    "bg": 2.86
  },
  "mp-1202506": {
    "bg": 1.22
  },
  "mp-29529": {
    "bg": 1.19
  },
  "mp-571102": {
    "bg": 2.815
  },
  "mp-27653": {
    "bg": 4.67
  },
  "mp-1178513": {
    "bg": 3.1
  },
  "mp-1191636": {
    "bg": 2.58
  },
  "mp-22791": {
    "bg": 0.86
  },
  "mp-569128": {
    "bg": 1.1
  },
  "mp-1224851": {
    "bg": 1.38
  },
  "mp-4394": {
    "bg": 4.19
  },
  "mp-1195253": {
    "bg": 4.0
  },
  "mp-23309": {
    "bg": 5.0
  },
  "mp-561232": {
    "bg": 2.54
  },
  "mp-540957": {
    "bg": 1.47
  },
  "mp-1195344": {
    "bg": 2.16
  },
  "mp-754329": {
    "bg": 3.0
  },
  "mp-1104878": {
    "bg": 1.62
  },
  "mp-11131": {
    "bg": 2.7
  },
  "mp-866615": {
    "bg": 2.7
  },
  "mp-4408": {
    "bg": 2.9
  },
  "mp-5909": {
    "bg": 4.5
  },
  "mp-3488": {
    "bg": 3.51
  },
  "mp-561103": {
    "bg": 3.8
  },
  "mp-6457": {
    "bg": 4.66
  },
  "mp-571171": {
    "bg": 1.83
  },
  "mp-9194": {
    "bg": 2.6
  },
  "mp-19281": {
    "bg": 1.33
  },
  "mp-1009750": {
    "bg": 0.92
  },
  "mp-20731": {
    "bg": 1.45
  },
  "mp-17905": {
    "bg": 1.63
  },
  "mp-573763": {
    "bg": 3.5
  },
  "mp-17464": {
    "bg": 3.185
  },
  "mp-6798": {
    "bg": 2.45
  },
  "mp-19455": {
    "bg": 1.96
  },
  "mp-776470": {
    "bg": 0.815
  },
  "mp-1342": {
    "bg": 3.56
  },
  "mp-1191240": {
    "bg": 4.24
  },
  "mp-1196950": {
    "bg": 3.79
  },
  "mp-3285": {
    "bg": 3.3
  },
  "mp-23177": {
    "bg": 2.6
  },
  "mp-849286": {
    "bg": 4.13
  },
  "mp-570324": {
    "bg": 2.14
  },
  "mp-555587": {
    "bg": 2.59
  },
  "mp-4156": {
    "bg": 4.74
  },
  "mp-4092": {
    "bg": 4.75
  },
  "mp-1095255": {
    "bg": 1.96
  },
  "mp-17947": {
    "bg": 2.465
  },
  "mp-998552": {
    "bg": 3.0
  },
  "mp-17612": {
    "bg": 4.2605
  },
  "mp-560459": {
    "bg": 4.855
  },
  "mp-1194731": {
    "bg": 2.06
  },
  "mp-769271": {
    "bg": 4.55
  },
  "mp-1195363": {
    "bg": 2.62
  },
  "mp-567681": {
    "bg": 2.3
  },
  "mp-629458": {
    "bg": 1.7000000000000002
  },
  "mp-3175": {
    "bg": 3.55
  },
  "mp-1190528": {
    "bg": 2.6
  },
  "mp-1199265": {
    "bg": 2.79
  },
  "mp-20546": {
    "bg": 2.94
  },
  "mp-1195298": {
    "bg": 0.97
  },
  "mp-608555": {
    "bg": 2.14
  },
  "mp-1080650": {
    "bg": 2.7
  },
  "mp-1105212": {
    "bg": 2.6
  },
  "mp-18449": {
    "bg": 4.18
  },
  "mp-1219046": {
    "bg": 1.5
  },
  "mp-1195251": {
    "bg": 2.0
  },
  "mp-18664": {
    "bg": 2.385
  },
  "mp-1206662": {
    "bg": 1.04
  },
  "mp-754206": {
    "bg": 3.35
  },
  "mp-2352": {
    "bg": 1.53
  },
  "mp-559186": {
    "bg": 3.53
  },
  "mp-567504": {
    "bg": 1.09
  },
  "mp-1207082": {
    "bg": 1.875
  },
  "mp-556911": {
    "bg": 2.0
  },
  "mp-1189528": {
    "bg": 3.645
  },
  "mp-1078295": {
    "bg": 3.08
  },
  "mp-1224946": {
    "bg": 3.0
  },
  "mp-556850": {
    "bg": 1.0
  },
  "mp-1045": {
    "bg": 3.875
  },
  "mp-23804": {
    "bg": 1.875
  },
  "mp-555269": {
    "bg": 2.1125
  },
  "mp-569715": {
    "bg": 1.2
  },
  "mp-1180473": {
    "bg": 0.59
  },
  "mp-9490": {
    "bg": 1.63
  },
  "mp-24354": {
    "bg": 4.8100000000000005
  },
  "mp-560835": {
    "bg": 1.8900000000000001
  },
  "mp-684504": {
    "bg": 3.5
  },
  "mp-1203387": {
    "bg": 2.51
  },
  "mp-8484": {
    "bg": 3.6
  },
  "mp-545482": {
    "bg": 2.75
  },
  "mp-18751": {
    "bg": 2.12
  },
  "mp-1190698": {
    "bg": 2.04
  },
  "mp-552806": {
    "bg": 3.71
  },
  "mp-5038": {
    "bg": 3.305
  },
  "mp-1199451": {
    "bg": 3.75
  },
  "mp-1095289": {
    "bg": 1.57
  },
  "mp-1215701": {
    "bg": 1.05
  },
  "mp-19049": {
    "bg": 2.95
  },
  "mp-866503": {
    "bg": 2.52
  },
  "mp-28421": {
    "bg": 2.34
  },
  "mp-1195033": {
    "bg": 1.3
  },
  "mp-556541": {
    "bg": 1.8
  },
  "mp-1559": {
    "bg": 2.03
  },
  "mp-558521": {
    "bg": 4.64
  },
  "mp-13979": {
    "bg": 2.14
  },
  "mp-1228703": {
    "bg": 1.8
  },
  "mp-1224070": {
    "bg": 3.4
  },
  "mp-557373": {
    "bg": 1.74
  },
  "mp-2809": {
    "bg": 1.7
  },
  "mp-1222398": {
    "bg": 2.64
  },
  "mp-1190487": {
    "bg": 2.93
  },
  "mp-19330": {
    "bg": 3.1
  },
  "mp-1180682": {
    "bg": 1.0
  },
  "mp-1200759": {
    "bg": 3.0
  },
  "mp-14577": {
    "bg": 2.58
  },
  "mp-4988": {
    "bg": 1.3
  },
  "mp-1195788": {
    "bg": 3.3
  },
  "mp-568949": {
    "bg": 2.68
  },
  "mp-35493": {
    "bg": 3.6
  },
  "mp-1217322": {
    "bg": 1.58
  },
  "mp-21705": {
    "bg": 1.6400000000000001
  },
  "mp-1190380": {
    "bg": 2.0
  },
  "mp-758022": {
    "bg": 3.4
  },
  "mp-1634": {
    "bg": 1.5
  },
  "mp-4200": {
    "bg": 4.255000000000001
  },
  "mp-569224": {
    "bg": 2.41
  },
  "mp-574620": {
    "bg": 2.35
  },
  "mp-1204598": {
    "bg": 3.1
  },
  "mp-4975": {
    "bg": 3.6825
  },
  "mp-13872": {
    "bg": 0.97
  },
  "mp-1205352": {
    "bg": 1.735
  },
  "mp-22841": {
    "bg": 2.47
  },
  "mp-1194282": {
    "bg": 3.4
  },
  "mp-2231": {
    "bg": 1.3
  },
  "mp-552454": {
    "bg": 1.99
  },
  "mp-2718": {
    "bg": 1.82
  },
  "mp-1196917": {
    "bg": 2.9
  },
  "mp-23423": {
    "bg": 3.1
  },
  "mp-2469": {
    "bg": 2.14
  },
  "mp-1211763": {
    "bg": 3.04
  },
  "mp-1004532": {
    "bg": 3.78
  },
  "mp-561533": {
    "bg": 3.0
  },
  "mp-2383161": {
    "bg": 2.7
  },
  "mp-557441": {
    "bg": 2.52
  },
  "mp-557": {
    "bg": 3.5
  },
  "mp-13383": {
    "bg": 1.55
  },
  "mp-1190429": {
    "bg": 2.47
  },
  "mp-1096782": {
    "bg": 1.0
  },
  "mp-849770": {
    "bg": 1.1
  },
  "mp-4165": {
    "bg": 2.4
  },
  "mp-505412": {
    "bg": 3.0
  },
  "mp-754654": {
    "bg": 3.75
  },
  "mp-11019": {
    "bg": 1.47
  },
  "mp-1198404": {
    "bg": 1.31
  },
  "mp-4199": {
    "bg": 0.98
  },
  "mp-36358": {
    "bg": 2.55
  },
  "mp-28240": {
    "bg": 3.35
  },
  "mp-1191234": {
    "bg": 3.4
  },
  "mp-22855": {
    "bg": 4.45
  },
  "mp-27742": {
    "bg": 3.36
  },
  "mp-1105584": {
    "bg": 2.4
  },
  "mp-29862": {
    "bg": 3.45
  },
  "mp-558760": {
    "bg": 1.53
  },
  "mp-1102857": {
    "bg": 0.5
  },
  "mp-27394": {
    "bg": 1.4125
  },
  "mp-5693": {
    "bg": 0.89
  },
  "mp-19097": {
    "bg": 2.35
  },
  "mp-1943": {
    "bg": 2.103
  },
  "mp-570321": {
    "bg": 1.35
  },
  "mp-8216": {
    "bg": 1.67
  },
  "mp-973966": {
    "bg": 4.27
  },
  "mp-1228557": {
    "bg": 3.4
  },
  "mp-1223262": {
    "bg": 2.6
  },
  "mp-571169": {
    "bg": 1.21
  },
  "mp-1196984": {
    "bg": 2.38
  },
  "mp-1225654": {
    "bg": 3.306
  },
  "mp-17835": {
    "bg": 1.47
  },
  "mp-999265": {
    "bg": 4.0
  },
  "mp-36539": {
    "bg": 0.61
  },
  "mp-683903": {
    "bg": 1.35
  },
  "mp-1191817": {
    "bg": 2.54
  },
  "mp-504466": {
    "bg": 2.925
  },
  "mp-1199946": {
    "bg": 0.93
  },
  "mp-4627": {
    "bg": 0.6000000000000001
  },
  "mp-804": {
    "bg": 3.4
  },
  "mp-22526": {
    "bg": 2.7
  },
  "mp-1203404": {
    "bg": 3.06
  },
  "mp-21459": {
    "bg": 1.9100000000000001
  },
  "mp-22996": {
    "bg": 1.662
  },
  "mp-547244": {
    "bg": 3.52
  },
  "mp-1246515": {
    "bg": 2.5
  },
  "mp-1192770": {
    "bg": 2.45
  },
  "mp-7611": {
    "bg": 2.4
  },
  "mp-22917": {
    "bg": 1.9835
  },
  "mp-10293": {
    "bg": 2.2
  },
  "mp-1079630": {
    "bg": 4.17
  },
  "mp-2030": {
    "bg": 1.55
  },
  "mp-1237135": {
    "bg": 3.05
  },
  "mp-1047075": {
    "bg": 1.89
  },
  "mp-7204": {
    "bg": 3.7
  },
  "mp-1195697": {
    "bg": 3.0
  },
  "mp-1018040": {
    "bg": 4.1
  },
  "mp-616458": {
    "bg": 1.8
  },
  "mp-552676": {
    "bg": 2.01
  },
  "mp-20282": {
    "bg": 2.55
  },
  "mp-1173567": {
    "bg": 3.6685
  },
  "mp-1271821": {
    "bg": 1.82
  },
  "mp-1204617": {
    "bg": 2.51
  },
  "mp-570339": {
    "bg": 2.815
  },
  "mp-540625": {
    "bg": 2.03
  },
  "mp-2843": {
    "bg": 1.3
  },
  "mp-23501": {
    "bg": 2.2
  },
  "mp-9763": {
    "bg": 2.8200000000000003
  },
  "mp-1227970": {
    "bg": 2.81
  },
  "mp-1204785": {
    "bg": 3.47
  },
  "mp-18814": {
    "bg": 3.104
  },
  "mp-1863": {
    "bg": 1.525
  },
  "mp-555186": {
    "bg": 2.87
  },
  "mp-10782": {
    "bg": 2.5
  },
  "mp-160": {
    "bg": 2.0
  },
  "mp-542545": {
    "bg": 1.53
  },
  "mp-1189383": {
    "bg": 3.1
  },
  "mp-554293": {
    "bg": 2.0
  },
  "mp-22323": {
    "bg": 3.02
  },
  "mp-10378": {
    "bg": 1.6
  },
  "mp-1195309": {
    "bg": 1.3900000000000001
  },
  "mp-7631": {
    "bg": 2.86
  },
  "mp-1195433": {
    "bg": 2.0
  },
  "mp-8624": {
    "bg": 2.75
  },
  "mp-23263": {
    "bg": 3.75
  },
  "mp-1202825": {
    "bg": 1.86
  },
  "mp-683905": {
    "bg": 1.45
  },
  "mp-1407369": {
    "bg": 2.0
  },
  "mp-641703": {
    "bg": 3.065
  },
  "mp-505526": {
    "bg": 2.725
  },
  "mp-1105201": {
    "bg": 2.13
  },
  "mp-568855": {
    "bg": 2.25
  },
  "mp-13313": {
    "bg": 0.79
  },
  "mp-1197024": {
    "bg": 2.54
  },
  "mp-12385": {
    "bg": 3.5
  },
  "mp-1202310": {
    "bg": 3.26
  },
  "mp-571637": {
    "bg": 1.93
  },
  "mp-570577": {
    "bg": 4.2
  },
  "mp-1192404": {
    "bg": 4.07
  },
  "mp-16818": {
    "bg": 2.37
  },
  "mp-19318": {
    "bg": 3.26
  },
  "mp-1194749": {
    "bg": 2.31
  },
  "mp-913": {
    "bg": 0.81
  },
  "mp-1223975": {
    "bg": 3.25
  },
  "mp-28230": {
    "bg": 1.68
  },
  "mp-985829": {
    "bg": 1.93
  },
  "mp-561639": {
    "bg": 2.8
  },
  "mp-1219182": {
    "bg": 0.51
  },
  "mp-23384": {
    "bg": 4.1850000000000005
  },
  "mp-1541": {
    "bg": 2.725
  },
  "mp-8016": {
    "bg": 2.65
  },
  "mp-5387": {
    "bg": 4.3
  },
  "mp-1112940": {
    "bg": 2.54
  },
  "mp-19048": {
    "bg": 3.2
  },
  "mp-505212": {
    "bg": 2.35
  },
  "mp-697331": {
    "bg": 1.6
  },
  "mp-1190898": {
    "bg": 4.05
  },
  "mp-3563": {
    "bg": 3.81
  },
  "mp-553910": {
    "bg": 2.0
  },
  "mp-17172": {
    "bg": 1.6
  },
  "mp-619461": {
    "bg": 2.73
  },
  "mp-1095618": {
    "bg": 1.06
  },
  "mp-2345": {
    "bg": 4.8
  },
  "mp-15221": {
    "bg": 2.64
  },
  "mp-12954": {
    "bg": 3.61
  },
  "mp-35421": {
    "bg": 2.7
  },
  "mp-1205397": {
    "bg": 2.31
  },
  "mp-769582": {
    "bg": 4.75
  },
  "mp-669410": {
    "bg": 2.0
  },
  "mp-28077": {
    "bg": 3.98
  },
  "mp-1602": {
    "bg": 2.95
  },
  "mp-607267": {
    "bg": 4.0
  },
  "mp-27614": {
    "bg": 2.67
  },
  "mp-1519": {
    "bg": 4.0
  },
  "mp-1192531": {
    "bg": 1.53
  },
  "mp-4175": {
    "bg": 1.3199999999999998
  },
  "mp-23352": {
    "bg": 3.25
  },
  "mp-1190564": {
    "bg": 4.05
  },
  "mp-19803": {
    "bg": 3.225
  },
  "mp-676241": {
    "bg": 0.685
  },
  "mp-1106127": {
    "bg": 2.27
  },
  "mp-570485": {
    "bg": 0.63
  },
  "mp-1106270": {
    "bg": 1.97
  },
  "mp-1095296": {
    "bg": 1.43
  },
  "mp-3642": {
    "bg": 3.3
  },
  "mp-18988": {
    "bg": 1.89
  },
  "mp-422": {
    "bg": 4.17
  },
  "mp-1103970": {
    "bg": 1.5
  },
  "mp-28800": {
    "bg": 0.53
  },
  "mp-510421": {
    "bg": 1.4
  },
  "mp-7280": {
    "bg": 1.38
  },
  "mp-1190588": {
    "bg": 4.59
  },
  "mp-1195594": {
    "bg": 2.31
  },
  "mp-3677": {
    "bg": 4.3
  },
  "mp-1216225": {
    "bg": 0.72
  },
  "mp-1102833": {
    "bg": 1.2
  },
  "mp-18531": {
    "bg": 2.26
  },
  "mp-1434": {
    "bg": 1.78
  },
  "mp-1960": {
    "bg": 3.24
  },
  "mp-16882": {
    "bg": 3.9
  }
}