{
    "mp-28911": {
        "bg": 3.44
    },
    "mp-23713": {
        "bg": 3.0
    },
    "mp-644203": {
        "bg": 3.17
    },
    "mp-571020": {
        "bg": 3.3
    },
    "mp-1078667": {
        "bg": 1.51
    },
    "mp-23956": {
        "bg": 3.46
    },
    "mp-23737": {
        "bg": 2.59
    },
    "mp-697905": {
        "bg": 0.8210000000000001
    },
    "mp-27653": {
        "bg": 4.67
    },
    "mp-23703": {
        "bg": 2.76
    },
    "mp-23709": {
        "bg": 2.9
    },
    "mp-23804": {
        "bg": 1.875
    },
    "mp-697331": {
        "bg": 1.6
    },
    "mp-23704": {
        "bg": 4.8
    },
    "mp-23949": {
        "bg": 3.32
    }
}